jupyter_ruff/__init__.py
jupyter_ruff/_version.py
jupyter_ruff-0.3.0.data/data/share/jupyter/labextensions/jupyter-ruff/package.json
jupyter_ruff-0.3.0.data/data/share/jupyter/labextensions/jupyter-ruff/schemas/jupyter-ruff/package.json.orig
jupyter_ruff-0.3.0.data/data/share/jupyter/labextensions/jupyter-ruff/schemas/jupyter-ruff/plugin.json
jupyter_ruff-0.3.0.data/data/share/jupyter/labextensions/jupyter-ruff/static/139.22a0c8271bdca0279090.js
jupyter_ruff-0.3.0.data/data/share/jupyter/labextensions/jupyter-ruff/static/139.22a0c8271bdca0279090.js.LICENSE.txt
jupyter_ruff-0.3.0.data/data/share/jupyter/labextensions/jupyter-ruff/static/402.3e4042d303a9cbb42bba.js
jupyter_ruff-0.3.0.data/data/share/jupyter/labextensions/jupyter-ruff/static/728.19b678dbded8d911f57c.js
jupyter_ruff-0.3.0.data/data/share/jupyter/labextensions/jupyter-ruff/static/729.486e52d75cf4c126728c.js
jupyter_ruff-0.3.0.data/data/share/jupyter/labextensions/jupyter-ruff/static/787.82042cd831fc011ed973.js
jupyter_ruff-0.3.0.data/data/share/jupyter/labextensions/jupyter-ruff/static/ec503327ce3757d0044c.wasm
jupyter_ruff-0.3.0.data/data/share/jupyter/labextensions/jupyter-ruff/static/remoteEntry.853a37cb3c52d40ecf02.js
jupyter_ruff-0.3.0.data/data/share/jupyter/labextensions/jupyter-ruff/static/style.js
jupyter_ruff-0.3.0.data/data/share/jupyter/labextensions/jupyter-ruff/static/third-party-licenses.json
jupyter_ruff-0.3.0.data/data/share/jupyter/labextensions/jupyter-ruff/install.json
jupyter_ruff-0.3.0.dist-info/METADATA
jupyter_ruff-0.3.0.dist-info/WHEEL
jupyter_ruff-0.3.0.dist-info/licenses/LICENSE
jupyter_ruff-0.3.0.dist-info/RECORD
